neutone_sdk/__init__.py
neutone_sdk/assets/default_samples/sample_ambience.mp3
neutone_sdk/assets/default_samples/sample_drums.mp3
neutone_sdk/assets/default_samples/sample_rhodes.mp3
neutone_sdk/audio.py
neutone_sdk/benchmark.py
neutone_sdk/cached_mel_spec.py
neutone_sdk/constants.py
neutone_sdk/conv.py
neutone_sdk/core.py
neutone_sdk/filters.py
neutone_sdk/gcn_1d.py
neutone_sdk/metadata.py
neutone_sdk/non_realtime_sqw.py
neutone_sdk/non_realtime_wrapper.py
neutone_sdk/parameter.py
neutone_sdk/py.typed
neutone_sdk/queues.py
neutone_sdk/realtime_stft.py
neutone_sdk/sandwich.py
neutone_sdk/sqw.py
neutone_sdk/tcn_1d.py
neutone_sdk/utils.py
neutone_sdk/wavform_to_wavform.py
neutone_sdk-1.5.2.dist-info/LICENSE
neutone_sdk-1.5.2.dist-info/METADATA
neutone_sdk-1.5.2.dist-info/WHEEL
neutone_sdk-1.5.2.dist-info/RECORD
