Metadata-Version: 2.1
Name: neutone_sdk
Version: 1.5.2
Summary: SDK for wrapping deep learning models for usage in the Neutone plugin
Home-page: https://github.com/QosmoInc/neutone_sdk.git
License: LGPL
Author: Qosmo
Author-email: contact@qosmo.jp
Requires-Python: >=3.8,<4.0
Classifier: License :: Other/Proprietary License
Classifier: Programming Language :: Python :: 3
Classifier: Programming Language :: Python :: 3.8
Classifier: Programming Language :: Python :: 3.9
Classifier: Programming Language :: Python :: 3.10
Classifier: Programming Language :: Python :: 3.11
Requires-Dist: click (>=8.1.7,<9.0.0)
Requires-Dist: jsonschema (>=4.21.0,<5.0.0)
Requires-Dist: numpy (>=1.21.6,<2.3.0)
Requires-Dist: requests (>=2.27.1,<3.0.0)
Requires-Dist: soundfile (>=0.12.1)
Requires-Dist: torch (>=1.11.0,<3.0.0)
Requires-Dist: torchaudio (>=0.11.0,<3.0.0)
Requires-Dist: tqdm (>=4.63.1,<5.0.0)
